netbox_catalyst_center/__init__.py
netbox_catalyst_center/catalyst_client.py
netbox_catalyst_center/forms.py
netbox_catalyst_center/navigation.py
netbox_catalyst_center/urls.py
netbox_catalyst_center/views.py
netbox_catalyst_center/templates/netbox_catalyst_center/client_tab.html
netbox_catalyst_center/templates/netbox_catalyst_center/comparison.html
netbox_catalyst_center/templates/netbox_catalyst_center/import.html
netbox_catalyst_center/templates/netbox_catalyst_center/network_device_tab.html
netbox_catalyst_center/templates/netbox_catalyst_center/settings.html
netbox_catalyst_center-1.3.5.dist-info/licenses/LICENSE
netbox_catalyst_center-1.3.5.dist-info/METADATA
netbox_catalyst_center-1.3.5.dist-info/WHEEL
netbox_catalyst_center-1.3.5.dist-info/top_level.txt
netbox_catalyst_center-1.3.5.dist-info/RECORD
